{
    "@class": "com.kony.gen.viz.model.component.KVizLabel",
    "DNDConfig": null,
    "__parentReadjusting__": false,
    "_height_": {
        "type": "ref",
        "value": "preferred"
    },
    "_left_": {
        "type": "string",
        "value": "25%"
    },
    "_margin_": [
        1,
        1,
        1,
        1
    ],
    "_padding_": [
        0,
        0,
        0,
        0
    ],
    "_skin_": "s6a7a54efc384b9598f1c0e8d63043cc",
    "_text_": "Label",
    "_top_": {
        "type": "string",
        "value": "97dp"
    },
    "_width_": {
        "type": "ref",
        "value": "preferred"
    },
    "_wrapping_": 2,
    "android": {
        "textStyle": {
            "letterSpacing": 0,
            "strikeThrough": false
        }
    },
    "canUpdateUI": true,
    "containerId": true,
    "containerweight": 100,
    "contentalignment": 4,
    "id": "ContactNotes",
    "info": null,
    "ipad": {
        "psp": {
            "wrapping": 2
        }
    },
    "iphone": {
        "psp": {
            "wrapping": 2
        }
    },
    "iscustomlayout": false,
    "isvisible": true,
    "kuid": "fe6d056738354d8db69fdb5c477e33bc",
    "name": "kony.ui.Label",
    "parent": "ContactRowContainer",
    "pf": "ContactRow",
    "retaincontentalignment": false,
    "retainflexpositionproperties": false,
    "textstyle": {},
    "tooltip": "",
    "wType": "Label",
    "zindex": 1
}